stinkbait/__init__.py
stinkbait/arguments.py
stinkbait/logger_config.py
stinkbait/main.py
stinkbait/session.py
stinkbait/orgs/__init__.py
stinkbait/orgs/orgs.py
stinkbait/playbooks/__init__.py
stinkbait/playbooks/playbooks.py
stinkbait/users/__init__.py
stinkbait/users/users.py
stinkbait-0.2.0.2.dist-info/METADATA
stinkbait-0.2.0.2.dist-info/WHEEL
stinkbait-0.2.0.2.dist-info/entry_points.txt
stinkbait-0.2.0.2.dist-info/top_level.txt
stinkbait-0.2.0.2.dist-info/zip-safe
stinkbait-0.2.0.2.dist-info/RECORD
