Metadata-Version: 2.1
Name: stinkbait
Version: 0.2.0.2
Summary: Security Awareness Testing and Training Tool
Home-page: https://github.com/traingrc/stinkbait
Author: Wes Ladd
Author-email: wesladd@traingrc.com
Project-URL: Code, https://github.com/traingrc/stinkbait
Project-URL: Documentation, https://traingrc.com
Project-URL: Example Report, https://traingrc.com
Keywords: aws cloud infrastructure for security awareness testing and training
Classifier: Programming Language :: Python :: 3
Classifier: License :: OSI Approved :: MIT License
Classifier: Operating System :: OS Independent
Requires-Python: >=3.6
Requires-Dist: bs4
Requires-Dist: boto3
Requires-Dist: botocore
Requires-Dist: argparse
Requires-Dist: jinja2
Requires-Dist: markdown
Requires-Dist: pyyaml
Requires-Dist: schema
Requires-Dist: stinkbait
